lazy_dev_ai/__init__.py
lazy_dev_ai/cli.py
lazy_dev_ai/files.py
lazy_dev_ai/llm.py
lazy_dev_ai/prompts/default_cleanup.txt
lazy_dev_ai/prompts/default_comment.txt
lazy_dev_ai/prompts/default_docstring.txt
lazy_dev_ai/prompts/defaults.py
lazy_dev_ai/templates/default_base.txt
lazy_dev_ai-0.2.3.dist-info/METADATA
lazy_dev_ai-0.2.3.dist-info/WHEEL
lazy_dev_ai-0.2.3.dist-info/entry_points.txt
lazy_dev_ai-0.2.3.dist-info/RECORD
