Metadata-Version: 2.1
Name: lazy-dev-ai
Version: 0.2.3
Summary: A simple tool for applying chatgpt prompts to code
Home-page: https://github.com/rsivilli/lazy-dev-ai
Author: Robert Sivilli
Author-email: robert.sivilli@gmail.com
Requires-Python: >=3.10,<4.0
Classifier: Programming Language :: Python :: 3
Classifier: Programming Language :: Python :: 3.10
Classifier: Programming Language :: Python :: 3.11
Classifier: Programming Language :: Python :: 3.12
Requires-Dist: click (>=8.1.7,<9.0.0)
Requires-Dist: openai (>=1.51.0,<2.0.0)
Requires-Dist: pydantic (>=2.9.2,<3.0.0)
Requires-Dist: python-dotenv (>=1.0.1,<2.0.0)
Project-URL: Repository, https://github.com/rsivilli/lazy-dev-ai
